setup.py
brazil_national_holidays/__init__.py
brazil_national_holidays/brazil_national_holidays.py
brazil_national_holidays.egg-info/PKG-INFO
brazil_national_holidays.egg-info/SOURCES.txt
brazil_national_holidays.egg-info/dependency_links.txt
brazil_national_holidays.egg-info/not-zip-safe
brazil_national_holidays.egg-info/top_level.txt