Metadata-Version: 2.1
Name: brazil-national-holidays
Version: 1.0.0
Summary: Manipulates dates based on country holidays
Home-page: UNKNOWN
Author: Vinícius Gomes Vieira
License: UNKNOWN
Platform: UNKNOWN
